static/__init__.py
static/js/__init__.py
static/xterm/__init__.py
templates/__init__.py
webconsole/__init__.py
webconsole/docker/__init__.py
webconsole/docker/docker_console.py
webconsole/linux/__init__.py
webconsole/linux/linux_console.py
webconsole/static/__init__.py
webconsole/static/js/__init__.py
webconsole/static/js/jquery-1.12.4.js
webconsole/static/xterm/LICENSE
webconsole/static/xterm/README.md
webconsole/static/xterm/__init__.py
webconsole/static/xterm/bower.json
webconsole/static/xterm/gulpfile.js
webconsole/static/xterm/jsdoc.json
webconsole/static/xterm/package.json
webconsole/static/xterm/tsconfig.json
webconsole/static/xterm/tslint.json
webconsole/static/xterm/typings.json
webconsole/static/xterm/dist/xterm.css
webconsole/static/xterm/dist/xterm.js
webconsole/static/xterm/dist/xterm.js.map
webconsole/static/xterm/dist/addons/attach/attach.js
webconsole/static/xterm/dist/addons/attach/package.json
webconsole/static/xterm/dist/addons/fit/fit.js
webconsole/static/xterm/dist/addons/fit/package.json
webconsole/static/xterm/dist/addons/fullscreen/fullscreen.css
webconsole/static/xterm/dist/addons/fullscreen/fullscreen.js
webconsole/static/xterm/dist/addons/fullscreen/package.json
webconsole/static/xterm/dist/addons/linkify/linkify.js
webconsole/static/xterm/dist/addons/search/search.js
webconsole/static/xterm/dist/addons/search/search.js.map
webconsole/static/xterm/dist/addons/terminado/package.json
webconsole/static/xterm/dist/addons/terminado/terminado.js
webconsole/static/xterm/lib/Buffer.js
webconsole/static/xterm/lib/Buffer.js.map
webconsole/static/xterm/lib/Buffer.test.js
webconsole/static/xterm/lib/Buffer.test.js.map
webconsole/static/xterm/lib/BufferSet.js
webconsole/static/xterm/lib/BufferSet.js.map
webconsole/static/xterm/lib/BufferSet.test.js
webconsole/static/xterm/lib/BufferSet.test.js.map
webconsole/static/xterm/lib/Charsets.js
webconsole/static/xterm/lib/Charsets.js.map
webconsole/static/xterm/lib/CompositionHelper.js
webconsole-0.0.7.dist-info/METADATA
webconsole-0.0.7.dist-info/WHEEL
webconsole-0.0.7.dist-info/top_level.txt
webconsole-0.0.7.dist-info/RECORD
