Metadata-Version: 2.1
Name: webconsole
Version: 0.0.7
Summary: webconsole
Author: RayCheung
Keywords: pip,webconsole,python,docker
Classifier: Programming Language :: Python :: 3
Classifier: License :: OSI Approved :: MIT License
Classifier: Operating System :: OS Independent
Requires-Dist: websockets (==10.4)
Requires-Dist: docker (==5.0.0)
Requires-Dist: setuptools (==65.6.3)
Requires-Dist: paramiko (==3.1.0)
